Workbook

Sheet input
A1: Inputs (AWS us-east-1 / N. Virginia) — Workload + Pricing knobs (low-concurrency optimized)
A2: Section | B2: Parameter | C2: Min | D2: Max | E2: Unit | F2: Notes
A4: Workload | B4: Monthly total jobs | C4: 28000 | D4: 50000 | E4: jobs/month
A5: Workload | B5: Daily total jobs | C5: 1200 | D5: 1800 | E5: jobs/day
A6: Workload | B6: Hourly total jobs | C6: 120 | D6: 150 | E6: jobs/hour | F6: Peak hour
A7: Data mix | B7: Small jobs share | C7: 0.8 | D7: 0.8 | E7: ratio | F7: 80%
A8: Data mix | B8: Small job size | C8: 200 | D8: 200 | E8: MB/job
A9: Data mix | B9: Large jobs share | C9: 0.2 | D9: 0.2 | E9: ratio | F9: 20%
A10: Data mix | B10: Large job size | C10: 3 | D10: 3 | E10: GB/job
A11: Data mix | B11: Max job size (some jobs) | C11: 6 | D11: 6 | E11: GB/job
A12: Runtime | B12: Small job avg runtime (assumes lightweight transforms) | C12: 3 | D12: 5 | E12: minutes/job | F12: Tune later
A13: Runtime | B13: Large job avg runtime (assumes joins/agg; slower OK) | C13: 15 | D13: 25 | E13: minutes/job | F13: Tune later
A14: Runtime | B14: Driver nodes per job cluster | C14: 1 | D14: 1 | E14: nodes
A15: Runtime | B15: Small job worker nodes (reduced for low concurrency) | C15: 1 | D15: 1 | E15: nodes
A16: Runtime | B16: Large job worker nodes (reduced for low concurrency) | C16: 2 | D16: 2 | E16: nodes
A17: Runtime | B17: Overhead factor (autoscale/idle) | C17: 1.05 | D17: 1.05 | E17: multiplier | F17: Buffer
A18: Databricks | B18: EC2 $/node-hour (on-demand, us-east-1). Example: m6i.large=$0.096/hr, m6i.xlarge=$0.192/hr. | C18: 0.096 | D18: 0.192 | E18: $/node-hour | F18: Example m6i.xlarge
A19: Databricks | B19: DBU price (Jobs Compute). Standard tier often ~$0.10/DBU; Premium/Enterprise may be higher. | C19: 0.1 | D19: 0.15 | E19: $/DBU | F19: Fill from Databricks pricing
A20: Databricks | B20: DBU per node-hour (depends on instance + compute type). Lower if using smaller nodes / optimized config. | C20: 2 | D20: 3 | E20: DBU/node-hour | F20: Depends on compute type
A21: Databricks license/support (fixed $/month, optional) | B21: If your Databricks contract has separate platform/support fees. Often DBU already includes this; keep 0 if none. | C21: 0 | D21: 0 | E21: $/month | F21: Unity Catalog/monitoring buffer
A22: Airflow (self) | B22: Hours per month | C22: 730 | D22: 730 | E22: hours
A23: Airflow (self) | B23: EC2 instances | C23: 2 | D23: 2 | E23: instances | F23: Web/Scheduler + Worker
A24: Airflow (self) | B24: EC2 $/instance-hour | C24: 0.0832 | D24: 0.0832 | E24: $/hour | F24: Example t3a.large
A25: Airflow (self) | B25: EBS per instance | C25: 50 | D25: 50 | E25: GB | F25: gp3
A26: Airflow (self) | B26: EBS $/GB-month | C26: 0.08 | D26: 0.08 | E26: $/GB-month | F26: gp3
A27: Airflow (self) | B27: Misc (ALB/NAT/Logs) | C27: 75 | D27: 125 | E27: $/month | F27: Placeholder
A28: MWAA | B28: MWAA hourly rate | C28: 0.49 | D28: 0.99 | E28: $/hour | F28: Small..Large example; replace
A29: MWAA | B29: MWAA misc (logs/NAT/S3) | C29: 50 | D29: 100 | E29: $/month | F29: Placeholder
A30: Databricks | B30: EC2 discount factor (Savings Plan/Spot) | C30: 0.6 | D30: 1 | E30: multiplier

Sheet workload_calcs
A1: Workload calculations (derived from input)
A2: Item | B2: Min | C2: Max | D2: Unit | E2: Formula/Notes
A4: Small jobs / month | B4: =input!C4*input!C7 | C4: =input!D4*input!C7 | D4: jobs/month | E4: Monthly×small_share
A5: Large jobs / month | B5: =input!C4*input!C9 | C5: =input!D4*input!C9 | D5: jobs/month | E5: Monthly×large_share
A6: Avg data per job (GB) | B6: =(input!C7*(input!C8/1024))+(input!C9*input!C10) | C6: =(input!C7*(input!C8/1024))+(input!C9*input!C10) | D6: GB/job | E6: Weighted avg
A7: Total data / month (GB) | B7: =B4*B6 | C7: =C4*C6 | D7: GB/month | E7: Jobs×avgGB
A8: Small runtime (hours) | B8: =input!C12/60 | C8: =input!C12/60 | D8: hours/job | E8: minutes/60
A9: Large runtime (hours) | B9: =input!C13/60 | C9: =input!C13/60 | D9: hours/job | E9: minutes/60
A10: Small cluster nodes (driver+workers) | B10: =input!C14+input!C15 | C10: =input!C14+input!C15 | D10: nodes
A11: Large cluster nodes (driver+workers) | B11: =input!C14+input!C16 | C11: =input!C14+input!C16 | D11: nodes
A12: Small jobs node-hours/month | B12: =B4*B8*B10 | C12: =C4*B8*B10 | D12: node-hours | E12: jobs×hrs×nodes
A13: Large jobs node-hours/month | B13: =B5*B9*B11 | C13: =C5*B9*B11 | D13: node-hours | E13: jobs×hrs×nodes
A14: Total node-hours/month (with overhead) | B14: =(B12+B13)*input!C17 | C14: =(C12+C13)*input!C17 | D14: node-hours | E14: Sum×overhead
A15: Avg nodes running (capacity proxy) | B15: =B14/input!C22 | C15: =C14/input!C22 | D15: nodes | E15: node-hours / hours per month
A16: Estimated concurrency (peak hour, rough) | B16: =input!C6*B8 | C16: =input!D6*B8 | D16: jobs | E16: hourly_jobs×small_runtime_hrs

Sheet databricks_compute_budget
A1: Databricks (Jobs Compute) monthly cost — us-east-1
A2: Item | B2: Min | C2: Max | D2: Unit | E2: Formula/Notes
A4: Effective $/node-hour | B4: =(input!C18*input!C30) + (input!C20*input!C19) | C4: =(input!D18*input!D30) + (input!D20*input!D19) | D4: $/node-hour | E4: EC2 (blended) + DBU cost
A5: Node-hours/month (from workload_calcs) | B5: =workload_calcs!B14 | C5: =workload_calcs!C14 | D5: node-hours | E5: Includes overhead
A6: Compute cost | B6: =B4*B5 | C6: =C4*C5 | D6: $/month | E6: node-hours×$/node-hour
A7: Databricks license/support (fixed) | B7: =input!C21 | C7: =input!D21 | D7: $/month | E7: Optional fixed fee (set 0 if none)
A8: Total Databricks monthly | B8: =B6+B7 | C8: =C6+C7 | D8: $/month

Sheet mwaa
A1: MWAA monthly cost — us-east-1 (Virginia)
A2: Item | B2: Min | C2: Max | D2: Unit | E2: Formula/Notes
A4: MWAA environment | B4: =input!C28*input!C22 | C4: =input!D28*input!D22 | D4: $/month | E4: rate×hours
A5: MWAA misc | B5: =input!C29 | C5: =input!D29 | D5: $/month | E5: placeholder
A6: Total MWAA | B6: =B4+B5 | C6: =C4+C5 | D6: $/month

Sheet airflow
A1: Airflow self-managed monthly cost — us-east-1
A2: Item | B2: Min | C2: Max | D2: Unit | E2: Formula/Notes
A4: EC2 compute | B4: =input!C23*input!C24*input!C22 | C4: =input!D23*input!D24*input!D22 | D4: $/month | E4: instances×$/hr×hrs
A5: EBS storage | B5: =input!C23*input!C25*input!C26 | C5: =input!D23*input!D25*input!D26 | D5: $/month | E5: instances×GB×rate
A6: Misc infra | B6: =input!C27 | C6: =input!D27 | D6: $/month | E6: placeholder
A7: Total Airflow self-managed | B7: =B4+B5+B6 | C7: =C4+C5+C6 | D7: $/month

Sheet budget_summary
A1: Budget summary — Databricks + Airflow (us-east-1)
A2: Scenario | B2: Min | C2: Max | D2: Unit | E2: Notes
A4: Databricks compute total | B4: =databricks_compute_budget!B8 | C4: =databricks_compute_budget!C8 | D4: $/month
A5: Airflow self-managed total | B5: =airflow!B7 | C5: =airflow!C7 | D5: $/month
A6: MWAA total (alternative) | B6: =mwaa!B6 | C6: =mwaa!C6 | D6: $/month
A7: Total (Databricks + self-managed Airflow) | B7: =B4+B5 | C7: =C4+C5 | D7: $/month
A8: Total (Databricks + MWAA) | B8: =B4+B6 | C8: =C4+C6 | D8: $/month
A9: Annual (Databricks + self-managed Airflow) | B9: =B7*12 | C9: =C7*12 | D9: $/year
A10: Annual (Databricks + MWAA) | B10: =B8*12 | C10: =C8*12 | D10: $/year
